LICENSE
MANIFEST.in
README.md
pyproject.toml
setup.py
tox.ini
src/Pegasus/__init__.py
src/Pegasus/analyzer.py
src/Pegasus/cluster.py
src/Pegasus/command.py
src/Pegasus/exitcode.py
src/Pegasus/init.py
src/Pegasus/kickstart.py
src/Pegasus/properties.py
src/Pegasus/replica_catalog.py
src/Pegasus/site_catalog.py
src/Pegasus/statistics.py
src/Pegasus/submitdir.py
src/Pegasus/transformation_catalog.py
src/Pegasus/user.py
src/Pegasus/workflow.py
src/Pegasus/cli/__init__.py
src/Pegasus/cli/pegasus-analyzer.py
src/Pegasus/cli/pegasus-config.py
src/Pegasus/cli/pegasus-cwl-converter.py
src/Pegasus/cli/pegasus-dagman.py
src/Pegasus/cli/pegasus-db-admin.py
src/Pegasus/cli/pegasus-em.py
src/Pegasus/cli/pegasus-exitcode.py
src/Pegasus/cli/pegasus-graphviz.py
src/Pegasus/cli/pegasus-init.py
src/Pegasus/cli/pegasus-metadata.py
src/Pegasus/cli/pegasus-monitord.py
src/Pegasus/cli/pegasus-newanalyzer.py
src/Pegasus/cli/pegasus-preflight-check.py
src/Pegasus/cli/pegasus-remove.py
src/Pegasus/cli/pegasus-run.py
src/Pegasus/cli/pegasus-service.py
src/Pegasus/cli/pegasus-statistics.py
src/Pegasus/cli/pegasus-status.py
src/Pegasus/cli/pegasus-submitdir.py
src/Pegasus/db/__init__.py
src/Pegasus/db/base_loader.py
src/Pegasus/db/connection.py
src/Pegasus/db/dashboard_loader.py
src/Pegasus/db/ensembles.py
src/Pegasus/db/errors.py
src/Pegasus/db/expunge.py
src/Pegasus/db/schema.py
src/Pegasus/db/workflow_loader.py
src/Pegasus/db/admin/__init__.py
src/Pegasus/db/admin/admin_loader.py
src/Pegasus/db/admin/commands.py
src/Pegasus/db/admin/versions/__init__.py
src/Pegasus/db/admin/versions/base_version.py
src/Pegasus/db/admin/versions/v0.py
src/Pegasus/db/admin/versions/v1.py
src/Pegasus/db/admin/versions/v10.py
src/Pegasus/db/admin/versions/v11.py
src/Pegasus/db/admin/versions/v12.py
src/Pegasus/db/admin/versions/v13.py
src/Pegasus/db/admin/versions/v14.py
src/Pegasus/db/admin/versions/v2.py
src/Pegasus/db/admin/versions/v3.py
src/Pegasus/db/admin/versions/v4.py
src/Pegasus/db/admin/versions/v5.py
src/pegasus_wms.egg-info/PKG-INFO
src/pegasus_wms.egg-info/SOURCES.txt
src/pegasus_wms.egg-info/dependency_links.txt
src/pegasus_wms.egg-info/not-zip-safe
src/pegasus_wms.egg-info/requires.txt
src/pegasus_wms.egg-info/top_level.txt
